gw3/__init__.py
gw3/client.py
gw3-0.6.5.dist-info/METADATA
gw3-0.6.5.dist-info/WHEEL
gw3-0.6.5.dist-info/top_level.txt
gw3-0.6.5.dist-info/RECORD
