Metadata-Version: 2.1
Name: gw3
Version: 0.6.5
Summary: A Python client for the Gateway3 API
Home-page: https://github.com/photon-storage/gw3-sdk-python
Author: photon team
Author-email: admin@photon.storage
License: UNKNOWN
Keywords: gw3,ipfs,gateway3
Platform: UNKNOWN
Classifier: Development Status :: 3 - Alpha
Classifier: Intended Audience :: Developers
Classifier: License :: OSI Approved :: MIT License
Classifier: Programming Language :: Python :: 3
Classifier: Programming Language :: Python :: 3.7
Classifier: Programming Language :: Python :: 3.8
Classifier: Programming Language :: Python :: 3.9
Requires-Python: >=3.7, <4
Requires-Dist: requests
